CHANGES.md
LICENSE.txt
MANIFEST.in
README.md
setup.cfg
setup.py
bogglesolver/__init__.py
bogglesolver/boggle_board.py
bogglesolver/cli.py
bogglesolver/load_english_dictionary.py
bogglesolver/solve_boggle.py
bogglesolver/twl06.py
bogglesolver.egg-info/PKG-INFO
bogglesolver.egg-info/SOURCES.txt
bogglesolver.egg-info/dependency_links.txt
bogglesolver.egg-info/entry_points.txt
bogglesolver.egg-info/top_level.txt
bogglesolver/test/__init__.py
bogglesolver/test/cli_tests.py
bogglesolver/test/integration_tests.py
bogglesolver/test/unit_tests.py