Metadata-Version: 1.1
Name: bogglesolver
Version: 0.0.1
Summary: Boggle Solver is a Python 3 package for solving Boggle boards.
Home-page: http://pypi.python.org/pypi/BoggleSolver
Author: Theo Voss
Author-email: theo.voss973@gmail.com
License: LGPL
Platform: UNKNOWN
Classifier: Development Status :: 1 - Planning
Classifier: Natural Language :: English
Classifier: Operating System :: OS Independent
Classifier: Programming Language :: Python :: 3.4
